testit/__init__.py
testit/__main__.py
testit/main.py
TestIt-0.1.0.dist-info/METADATA
TestIt-0.1.0.dist-info/WHEEL
TestIt-0.1.0.dist-info/entry_points.txt
TestIt-0.1.0.dist-info/top_level.txt
TestIt-0.1.0.dist-info/RECORD
